Metadata-Version: 2.4
Name: mpesa-python-sdk
Version: 1.0.0
Summary: A Python SDK for seamless integration with the M-Pesa API, supporting STK Push payments, C2B, B2C payouts, and more.
Home-page: https://github.com/Safaricom-Ethiopia-PLC/mpesa-python-sdk
Author: Zelalem Gizachew
Author-email: Zelalem Gizachew <zelalem.gizachew@safaricom.et>
License: MIT License
Project-URL: Homepage, https://github.com/Safaricom-Ethiopia-PLC/mpesa-python-sdk
Project-URL: Repository, https://github.com/Safaricom-Ethiopia-PLC/mpesa-python-sdk
Classifier: Programming Language :: Python :: 3
Classifier: License :: OSI Approved :: MIT License
Classifier: Operating System :: OS Independent
Requires-Python: >=3.7
License-File: LICENSE
Requires-Dist: pydantic<3.0.0,>=2.10.0
Requires-Dist: requests<3.0.0,>=2.31.0
Requires-Dist: python-dotenv<2.0.0,>=1.0.1
Requires-Dist: requests-oauthlib<3.0.0,>=2.0.0
Requires-Dist: requests-toolbelt<2.0.0,>=1.0.0
Provides-Extra: dev
Requires-Dist: build; extra == "dev"
Requires-Dist: pycodestyle==2.11.1; extra == "dev"
Requires-Dist: requests-unixsocket==0.2.0; extra == "dev"
Requires-Dist: typing-extensions==4.12.2; extra == "dev"
Dynamic: author
Dynamic: classifier
Dynamic: home-page
Dynamic: license-file
Dynamic: provides-extra
Dynamic: requires-python
